enflows/__init__.py
enflows/version.py
enflows/CNF/__init__.py
enflows/CNF/cnf.py
enflows/CNF/neural_odes/__init__.py
enflows/CNF/neural_odes/odefunc.py
enflows/CNF/neural_odes/squeeze.py
enflows/CNF/neural_odes/util.py
enflows/CNF/neural_odes/diffeq_layers/__init__.py
enflows/CNF/neural_odes/diffeq_layers/basic.py
enflows/CNF/neural_odes/diffeq_layers/container.py
enflows/CNF/neural_odes/diffeq_layers/resnet.py
enflows/CNF/neural_odes/diffeq_layers/wrappers.py
enflows/CNF/neural_odes/wrappers/__init__.py
enflows/CNF/neural_odes/wrappers/cnf_regularization.py
enflows/datasets/__init__.py
enflows/datasets/base.py
enflows/datasets/plane.py
enflows/datasets/uci/__init__.py
enflows/datasets/uci/bsds300.py
enflows/datasets/uci/download.py
enflows/datasets/uci/gas.py
enflows/datasets/uci/hepmass.py
enflows/datasets/uci/miniboone.py
enflows/datasets/uci/power.py
enflows/datasets/uci/uci.py
enflows/datasets/uci/utils.py
enflows/distributions/__init__.py
enflows/distributions/base.py
enflows/distributions/discrete.py
enflows/distributions/mixture.py
enflows/distributions/normal.py
enflows/distributions/uniform.py
enflows/flows/__init__.py
enflows/flows/autoregressive.py
enflows/flows/base.py
enflows/flows/realnvp.py
enflows/nn/__init__.py
enflows/nn/nde/__init__.py
enflows/nn/nde/made.py
enflows/nn/nets/__init__.py
enflows/nn/nets/activations.py
enflows/nn/nets/extended_basic_nets.py
enflows/nn/nets/invertible_densenet.py
enflows/nn/nets/lipschitz_dense.py
enflows/nn/nets/mlp.py
enflows/nn/nets/nets_util.py
enflows/nn/nets/pila.py
enflows/nn/nets/resnet.py
enflows/nn/nets/spectral_norm.py
enflows/transforms/__init__.py
enflows/transforms/adaptive_sigmoids.py
enflows/transforms/base.py
enflows/transforms/conditional.py
enflows/transforms/conv.py
enflows/transforms/coupling.py
enflows/transforms/linear.py
enflows/transforms/lu.py
enflows/transforms/made.py
enflows/transforms/nonlinearities.py
enflows/transforms/normalization.py
enflows/transforms/orthogonal.py
enflows-0.0.1.dist-info/LICENSE.md
enflows-0.0.1.dist-info/METADATA
enflows-0.0.1.dist-info/WHEEL
enflows-0.0.1.dist-info/top_level.txt
enflows-0.0.1.dist-info/RECORD
