Metadata-Version: 2.1
Name: enflows
Version: 0.0.1
Summary: Normalizing flows in PyTorch. An extension of nflows.
Author: Fabricio Arend Torres, Marcello Massima Negri, Jonathan Aellen
License: MIT
Classifier: Programming Language :: Python :: 3
Classifier: License :: OSI Approved :: MIT License
Classifier: Operating System :: OS Independent
Classifier: Development Status :: 2 - Pre-Alpha 
License-File: LICENSE.md
Requires-Dist: matplotlib
Requires-Dist: numpy
Requires-Dist: tensorboard
Requires-Dist: torch
Requires-Dist: torchdiffeq
Requires-Dist: tqdm
Requires-Dist: umnn
Requires-Dist: ninja
Requires-Dist: scikit-learn
Requires-Dist: pandas <2.0
Requires-Dist: h5py
